fedivuln/__init__.py
fedivuln/conf_sample.py
fedivuln/config.py
fedivuln/monitoring.py
fedivuln/publish.py
fedivuln/register.py
fedivuln/search.py
fedivuln/stream.py
fedivuln/utils.py
fedivuln-1.4.1.dist-info/METADATA
fedivuln-1.4.1.dist-info/WHEEL
fedivuln-1.4.1.dist-info/entry_points.txt
fedivuln-1.4.1.dist-info/licenses/COPYING
fedivuln-1.4.1.dist-info/RECORD
