Metadata-Version: 2.4
Name: FediVuln
Version: 1.4.1
Summary: A client to gather vulnerability-related information from the Fediverse.
License-Expression: GPL-3.0-or-later
License-File: COPYING
Keywords: Vulnerability-Lookup,Vulnerability,CVE,Fediverse,Mastodon
Author: Cédric Bonhomme
Author-email: cedric.bonhomme@circl.lu
Requires-Python: >=3.10,<4.0
Classifier: Development Status :: 5 - Production/Stable
Classifier: Environment :: Console
Classifier: Intended Audience :: Developers
Classifier: Intended Audience :: Science/Research
Classifier: License :: OSI Approved :: GNU General Public License v3 or later (GPLv3+)
Classifier: Operating System :: POSIX :: Linux
Classifier: Programming Language :: Python :: 3
Classifier: Programming Language :: Python :: 3.10
Classifier: Programming Language :: Python :: 3.11
Classifier: Programming Language :: Python :: 3.12
Classifier: Programming Language :: Python :: 3.13
Classifier: Programming Language :: Python :: 3.14
Classifier: Topic :: Security
Requires-Dist: aiohttp (>=3.13.3,<4.0.0)
Requires-Dist: mastodon-py (>=1.8.1)
Requires-Dist: pyvulnerabilitylookup (>=2.2.0)
Requires-Dist: valkey (>=6.0.2)
Project-URL: Changelog, https://github.com/vulnerability-lookup/FediVuln/blob/main/CHANGELOG.md
Project-URL: Homepage, https://github.com/vulnerability-lookup/FediVuln
Project-URL: Repository, https://github.com/vulnerability-lookup/FediVuln
